itchat_helper/__init__.py
itchat_helper/interface.py
itchat_helper/user.py
itchat_helper/userlist.py
itchat_helper-0.1.0.dist-info/METADATA
itchat_helper-0.1.0.dist-info/WHEEL
itchat_helper-0.1.0.dist-info/top_level.txt
itchat_helper-0.1.0.dist-info/RECORD
