Metadata-Version: 2.1
Name: itchat-helper
Version: 0.1.0
Summary: UNKNOWN
Home-page: UNKNOWN
Author: Tao Xiang
Author-email: tao.xiang@tum.de
License: UNKNOWN
Platform: UNKNOWN
Classifier: Programming Language :: Python :: 3
Classifier: License :: OSI Approved :: MIT License
Requires-Dist: itchat
